{
  "botProfiles": {
    "User": {
      "id": "user",
      "name": "User",
      "description": "The user interacting with the bot",
      "appearance": "user",
      "pronoun": "he/him",
      "example_messages": []
    },
    "Bot": {
      "id": "assistant",
      "name": "Assistant",
      "description": "I am an AI assistant that helps users with photo animation and image generation tasks",
      "appearance": "bot",
      "pronoun": "she/her",
      "example_messages": [
        "I can help you animate your photos",
        "Describe what animation you'd like and I'll create it for you"
      ]
    }
  },
  "chatSettings": {
   "User": {
     "model_name": "roleplay",
    "allow_nsfw": true,
    "tasks": [],
    "enable_memory": false
   },
   "Bot": {
     "model_name": "roleplay",
    "allow_nsfw": true,
    "tasks": [
      "Engage in roleplay conversation with the user. Always preserve the original face from the identity image without modifying or altering facial features."
    ],
    "enable_memory": false
   }
  },
  "imageSettings": {
    "User": {
      "identity_image_url": "",
      "model_name": "base",
      "style": "realistic",
      "gender": "man",
      "skin_color": "pale",
      "allow_nsfw": true,
      "usage_mode": "off",
      "return_bs64": false
    },
    "Bot": {
      "identity_image_url": "",
      "model_name": "persona",
      "style": "realistic",
      "gender": "woman",
      "skin_color": "white",
      "allow_nsfw": true,
      "usage_mode": "force",
      "return_bs64": true
    }
  }
}
